qxbranch/quantum_feature_detector/__init__.py
qxbranch/quantum_feature_detector/circuit.py
qxbranch/quantum_feature_detector/circuit_base.py
qxbranch/quantum_feature_detector/circuit_generator.py
qxbranch/quantum_feature_detector/circuit_generator_base.py
qxbranch/quantum_feature_detector/circuit_generator_pyquil.py
qxbranch/quantum_feature_detector/circuit_pyquil.py
qxbranch/quantum_feature_detector/decoder.py
qxbranch/quantum_feature_detector/decoder_base.py
qxbranch/quantum_feature_detector/decoder_pyquil.py
qxbranch/quantum_feature_detector/encoder.py
qxbranch/quantum_feature_detector/encoder_base.py
qxbranch/quantum_feature_detector/encoder_pyquil.py
qxbranch/quantum_feature_detector/logging_service.py
qxbranch/quantum_feature_detector/plottable_circuit.py
qxbranch/quantum_feature_detector/plotting.py
qxbranch/quantum_feature_detector/quantum_feature_detector.py
qxbranch/quantum_feature_detector/quantum_model.py
qxbranch/quantum_feature_detector/quantum_transform.py
qxbranch/quantum_feature_detector/pyquil/__init__.py
qxbranch/quantum_feature_detector/pyquil/circuit.py
qxbranch/quantum_feature_detector/pyquil/circuit_generator.py
qxbranch/quantum_feature_detector/pyquil/decoder.py
qxbranch/quantum_feature_detector/pyquil/encoder.py
qxbranch.quantum_feature_detector-1.0.2.data/data/LICENSE-2.0.txt
qxbranch.quantum_feature_detector-1.0.2.data/data/README.rst
qxbranch.quantum_feature_detector-1.0.2.dist-info/METADATA
qxbranch.quantum_feature_detector-1.0.2.dist-info/RECORD
qxbranch.quantum_feature_detector-1.0.2.dist-info/WHEEL
qxbranch.quantum_feature_detector-1.0.2.dist-info/top_level.txt
