Metadata-Version: 2.1
Name: qxbranch.quantum-feature-detector
Version: 1.0.2
Summary: A Python application by QxBranch for running Quantum Feature Detectors
Home-page: http://www.qxbranch.com
Author: QxBranch, Inc.
Author-email: support@qxbranch.com
License: Copyright 2018 QxBranch, Inc.
Keywords: qxbranch,quantum,machine learning
Platform: UNKNOWN
Requires-Dist: numpy (==1.15.4)
Requires-Dist: pyquil (>=2.0.0)
Requires-Dist: matplotlib (==3.0.2)
Requires-Dist: scikit-learn (==0.20.0)
Requires-Dist: networkx (==2.2)
